django_conditional_views/__init__.py
django_conditional_views/elements/__init__.py
django_conditional_views/elements/base.py
django_conditional_views/elements/etag.py
django_conditional_views/elements/last_modified.py
django_conditional_views/helpers.py
django_conditional_views/views.py
django_conditional_views-0.1.3.dist-info/LICENSE.md
django_conditional_views-0.1.3.dist-info/WHEEL
django_conditional_views-0.1.3.dist-info/METADATA
django_conditional_views-0.1.3.dist-info/RECORD
