Metadata-Version: 2.1
Name: django-conditional-views
Version: 0.1.3
Summary: Simple Etag and Last-Modified mixins for class based views.
Home-page: https://github.com/cordery/django-conditional-views
License: MIT
Keywords: Django,Last-Modified,http,conditional requests,ETag
Author: Andrew Cordery
Author-email: cordery@gmail.com
Requires-Python: >=3.6,<4.0
Classifier: License :: OSI Approved :: MIT License
Classifier: Programming Language :: Python :: 3
Classifier: Programming Language :: Python :: 3.6
Classifier: Programming Language :: Python :: 3.7
Provides-Extra: docs
Requires-Dist: django (>=2.1,<3.0)
Requires-Dist: sphinx (>=1.7,<2.0); extra == "docs"
Requires-Dist: sphinx-autodoc-typehints (>=1.3,<2.0); extra == "docs"
